rocktick/__init__.py
rocktick/_base_client.py
rocktick/_client.py
rocktick/_compat.py
rocktick/_constants.py
rocktick/_exceptions.py
rocktick/_files.py
rocktick/_models.py
rocktick/_qs.py
rocktick/_resource.py
rocktick/_response.py
rocktick/_streaming.py
rocktick/_types.py
rocktick/_version.py
rocktick/pagination.py
rocktick/py.typed
rocktick/_utils/__init__.py
rocktick/_utils/_compat.py
rocktick/_utils/_datetime_parse.py
rocktick/_utils/_json.py
rocktick/_utils/_logs.py
rocktick/_utils/_proxy.py
rocktick/_utils/_reflection.py
rocktick/_utils/_resources_proxy.py
rocktick/_utils/_streams.py
rocktick/_utils/_sync.py
rocktick/_utils/_transform.py
rocktick/_utils/_typing.py
rocktick/_utils/_utils.py
rocktick/lib/.keep
rocktick/resources/__init__.py
rocktick/resources/cron.py
rocktick/resources/executions.py
rocktick/resources/jobs.py
rocktick/resources/tenants.py
rocktick/resources/verify.py
rocktick/types/__init__.py
rocktick/types/cron_create_params.py
rocktick/types/cron_job.py
rocktick/types/cron_list_params.py
rocktick/types/cron_list_response.py
rocktick/types/cron_update_params.py
rocktick/types/execution.py
rocktick/types/execution_list_params.py
rocktick/types/execution_list_response.py
rocktick/types/http_request.py
rocktick/types/http_request_param.py
rocktick/types/http_response.py
rocktick/types/job_create_params.py
rocktick/types/job_list_params.py
rocktick/types/job_list_response.py
rocktick/types/job_update_params.py
rocktick/types/one_off_job.py
rocktick/types/tenant.py
rocktick/types/tenant_create_params.py
rocktick/types/tenant_update_params.py
rocktick/types/verify_retrieve_response.py
rocktick-0.9.0.dist-info/METADATA
rocktick-0.9.0.dist-info/WHEEL
rocktick-0.9.0.dist-info/licenses/LICENSE
rocktick-0.9.0.dist-info/RECORD
